MANIFEST.in
README.rst
setup.py
django_neon/__init__.py
django_neon/admin.py
django_neon/apps.py
django_neon/urls.py
django_neon/views.py
django_neon.egg-info/PKG-INFO
django_neon.egg-info/SOURCES.txt
django_neon.egg-info/dependency_links.txt
django_neon.egg-info/not-zip-safe
django_neon.egg-info/top_level.txt
django_neon/migrations/0001_initial.py
django_neon/migrations/__init__.py
django_neon/models/__init__.py
django_neon/models/media.py
django_neon/models/page.py
django_neon/models/pane.py
django_neon/processing/__init__.py
django_neon/processing/markdown_extensions.py
django_neon/processing/markup.py
django_neon/processing/plugin.py
django_neon/processing/pygmentssupport.py
django_neon/templates/django_neon/neon_base.html
django_neon/test/test_markup.py
django_neon/test/test_page.py
django_neon/test/test_panes.py
django_neon/test/images/blank.png