Metadata-Version: 1.1
Name: django-neon
Version: 1.0.0
Summary: A CMS-Application for django-projects.
Home-page: http://www.example.com
Author: Klaus Bremer
Author-email: bremer@bremer-media.de
License: MIT
Keywords: django cms-application
Platform: UNKNOWN
Classifier: Development Status :: 4 - Beta
Classifier: Environment :: Web Environment
Classifier: Framework :: Django
Classifier: Intended Audience :: Developers
Classifier: License :: OSI Approved :: MIT License
Classifier: Natural Language :: English
Classifier: Programming Language :: Python
Classifier: Programming Language :: Python :: 3.4
Classifier: Programming Language :: Python :: 3.5
